vector_store_client/__init__.py
vector_store_client/base_client.py
vector_store_client/client.py
vector_store_client/client_extended.py
vector_store_client/exceptions.py
vector_store_client/models.py
vector_store_client/models_new.py
vector_store_client/models_old.py
vector_store_client/types.py
vector_store_client/utils.py
vector_store_client/validation.py
vector_store_client/vst_cli.py
vector_store_client/adapters/__init__.py
vector_store_client/adapters/base_adapter.py
vector_store_client/adapters/embedding_adapter.py
vector_store_client/adapters/svo_adapter.py
vector_store_client/examples/__init__.py
vector_store_client/examples/advanced_usage.py
vector_store_client/examples/basic_usage.py
vector_store_client/examples/batch_operations.py
vector_store_client/examples/comprehensive_api_example.py
vector_store_client/examples/deletion_and_maintenance_example.py
vector_store_client/examples/error_handling.py
vector_store_client/examples/full_workflow_example.py
vector_store_client/examples/maintenance_operations.py
vector_store_client/examples/phase6_optimization_examples.py
vector_store_client/examples/simple_example.py
vector_store_client/examples/utilities_examples.py
vector_store_client/examples/working_api_example.py
vector_store_client/examples/write_all_types.py
vector_store_client/examples/use_cases/content_recommender.py
vector_store_client/examples/use_cases/qa_system.py
vector_store_client/examples/use_cases/semantic_search_engine.py
vector_store_client/middleware/__init__.py
vector_store_client/middleware/base_middleware.py
vector_store_client/middleware/caching_middleware.py
vector_store_client/middleware/logging_middleware.py
vector_store_client/middleware/metrics_middleware.py
vector_store_client/middleware/retry_middleware.py
vector_store_client/monitoring/__init__.py
vector_store_client/monitoring/health_checker.py
vector_store_client/monitoring/metrics_collector.py
vector_store_client/monitoring/performance_monitor.py
vector_store_client-2.0.0.3.dist-info/licenses/LICENSE
vector_store_client-2.0.0.3.dist-info/METADATA
vector_store_client-2.0.0.3.dist-info/WHEEL
vector_store_client-2.0.0.3.dist-info/entry_points.txt
vector_store_client-2.0.0.3.dist-info/top_level.txt
vector_store_client-2.0.0.3.dist-info/RECORD
