Metadata-Version: 2.4
Name: vector-store-client
Version: 2.0.0.3
Summary: Async client for Vector Store API with comprehensive JSON-RPC support
Home-page: https://github.com/vector-store/vector_store_client
Author: Vasily Zdanovskiy
Author-email: Vasily Zdanovskiy <vasilyvz@gmail.com>
License: MIT
Project-URL: Homepage, https://github.com/vasilyvz/vector_store_client
Project-URL: Documentation, https://github.com/vasilyvz/vector_store_client/docs
Project-URL: Repository, https://github.com/vasilyvz/vector_store_client.git
Project-URL: Issues, https://github.com/vasilyvz/vector_store_client/issues
Project-URL: Changelog, https://github.com/vasilyvz/vector_store_client/blob/main/CHANGELOG.md
Keywords: vector-store,semantic-search,embeddings,json-rpc,async
Classifier: Development Status :: 4 - Beta
Classifier: Intended Audience :: Developers
Classifier: License :: OSI Approved :: MIT License
Classifier: Programming Language :: Python :: 3
Classifier: Programming Language :: Python :: 3.8
Classifier: Programming Language :: Python :: 3.9
Classifier: Programming Language :: Python :: 3.10
Classifier: Programming Language :: Python :: 3.11
Classifier: Programming Language :: Python :: 3.12
Classifier: Topic :: Database
Classifier: Topic :: Scientific/Engineering :: Artificial Intelligence
Classifier: Topic :: Software Development :: Libraries :: Python Modules
Requires-Python: >=3.8
License-File: LICENSE
Requires-Dist: httpx>=0.24.0
Requires-Dist: pydantic>=2.0.0
Requires-Dist: chunk_metadata_adapter>=2.3.0
Requires-Dist: embed_client>=2.0.0
Requires-Dist: svo_client>=2.0.0
Requires-Dist: typing-extensions>=4.5.0
Requires-Dist: click>=8.0.0
Requires-Dist: numpy>=1.20.0
Requires-Dist: psutil>=5.8.0
Requires-Dist: aiohttp>=3.8.0
Provides-Extra: dev
Requires-Dist: pytest>=7.0.0; extra == "dev"
Requires-Dist: pytest-asyncio>=0.21.0; extra == "dev"
Requires-Dist: pytest-cov>=4.0.0; extra == "dev"
Requires-Dist: black>=23.0.0; extra == "dev"
Requires-Dist: isort>=5.12.0; extra == "dev"
Requires-Dist: mypy>=1.0.0; extra == "dev"
Requires-Dist: flake8>=6.0.0; extra == "dev"
Requires-Dist: pre-commit>=3.0.0; extra == "dev"
Provides-Extra: test
Requires-Dist: pytest>=7.0.0; extra == "test"
Requires-Dist: pytest-asyncio>=0.21.0; extra == "test"
Requires-Dist: pytest-cov>=4.0.0; extra == "test"
Requires-Dist: pytest-mock>=3.10.0; extra == "test"
Requires-Dist: aioresponses>=0.7.0; extra == "test"
Dynamic: author
Dynamic: home-page
Dynamic: license-file
Dynamic: requires-python
